pytpc/__init__.py
pytpc-0.1.0.dist-info/METADATA
pytpc-0.1.0.dist-info/WHEEL
pytpc-0.1.0.dist-info/RECORD
